airflow_grpc/__init__.py
airflow_grpc/grpc_hook.py
airflow_grpc/grpc_operator.py
airflow_grpc-0.0.10.dist-info/LICENSE
airflow_grpc-0.0.10.dist-info/METADATA
airflow_grpc-0.0.10.dist-info/WHEEL
airflow_grpc-0.0.10.dist-info/top_level.txt
airflow_grpc-0.0.10.dist-info/RECORD
