Metadata-Version: 2.1
Name: airflow-grpc
Version: 0.0.10
Summary: airflow grpc operator
Home-page: https://github.com/josephyin/airflow_grpc
Author: Joseph Yin
Author-email: josephyin@outlook.com
License: UNKNOWN
Platform: UNKNOWN
Classifier: Programming Language :: Python :: 3
Classifier: License :: OSI Approved :: MIT License
Classifier: Operating System :: OS Independent
Requires-Python: >=3.6
